CHANGELOG.rst
LICENSE
MANIFEST.in
README.rst
RELEASE.rst
setup.py
bin/moke
doc/Makefile
doc/source/conf.py
doc/source/conventions.rst
doc/source/examples.rst
doc/source/index.rst
src/moke/__init__.py
src/moke/core.py
src/moke/path.py
src/moke/util.py
src/moke.egg-info/PKG-INFO
src/moke.egg-info/SOURCES.txt
src/moke.egg-info/dependency_links.txt
src/moke.egg-info/not-zip-safe
src/moke.egg-info/top_level.txt
src/moke/data/mokefile.ini
src/moke/data/mokefile.py
test/test_core.py
test/test_util.py
test/data/grop.inp
test/data/sample.tsv
test/files/mokefile.py
test/functional/moke.log
test/functional/mokefile.ini
test/functional/mokefile.py
test/hidden/inp
test/hidden/moke.log
test/hidden/mokefile.ini
test/hidden/mokefile.py
test/hidden/out
test/required/moke.log
test/required/mokefile.ini
test/required/mokefile.py
test/scripts/grop.ini
test/scripts/grop.py
test/scripts/moke.log
test/scripts/mokefile.ini
test/scripts/mokefile.py
test/scripts/tworeq.ini
test/scripts/tworeq.py