Metadata-Version: 2.4
Name: moke
Version: 1.2.7
Summary: moke is not like make
Home-page: http://mcieslik-mctp.github.io/moke
Author: Marcin Cieslik
Author-email: mcieslik@med.umich.edu
License: BSD License
Keywords: make,ant,rake,paver,build,shell,argparse,bash
Classifier: Development Status :: 4 - Beta
Classifier: Operating System :: OS Independent
Classifier: Intended Audience :: Developers
Classifier: Programming Language :: Python :: 3
Classifier: License :: OSI Approved :: BSD License
License-File: LICENSE
Dynamic: author
Dynamic: author-email
Dynamic: classifier
Dynamic: description
Dynamic: home-page
Dynamic: keywords
Dynamic: license
Dynamic: license-file
Dynamic: summary
